geo2kml/__init__.py
geo2kml/geo_to_kml.py
geo2kml-0.0.3.dist-info/LICENSE
geo2kml-0.0.3.dist-info/METADATA
geo2kml-0.0.3.dist-info/WHEEL
geo2kml-0.0.3.dist-info/top_level.txt
geo2kml-0.0.3.dist-info/RECORD
